{"collaboration": false, "id": 1177, "cameraType": "Back Camera", "storyName": "pr_test", "experience": "AR", "mainStory": {"nodes": [{"name": "Scene1", "startTime": 0.0, "endTime": 10.0, "nodeId": 0, "nextNodeId": -1, "nodeType": "SceneNode", "nodeElements": [{"id": 3388, "order": 0, "node_id": 4785, "elementType": "Object3D", "object3D": {"objectId": 3388, "id": 1059, "name": "new chair", "dimensions": [0.0, 0.0, 0.0], "startTime": 0.0, "endTime": 10.0, "duration": 10.0, "layer": 1, "material": "0", "objectDbHash": 12, "origin": {"position": [0.0, 0.0, 0.0], "rotation": [0.0, 0.0, 0.0]}, "polygonCount": 0, "presenceDuration": 10.0, "rigType": "Humanoid", "scale": 1.0, "type": "Object3D", "iOSAssetBundle": "https://abxr-backend.s3.amazonaws.com/media/iOS_2_szyHDQb", "webglAssetBundle": "https://abxr-backend.s3.amazonaws.com/media/WebGL_1_PN3jwKo", "AndroidAssetBundle": null, "image_url": "https://abxr-backend.s3.amazonaws.com/media/-Mp7uWy0M4uMOtHk4Bt2_6WPSzes.jpg", "object3DElements": [{"id": 409, "type": "Movement", "node_element": 3388, "elementType": "Movement", "movement": {"id": 409, "intId": 409, "pathType": "Linear", "orientationType": "LookAhead", "startPointId": 613, "loopCount": false, "duration": 7.0, "entityOrientation": {"lookAhead": true, "lookAtTarget": "", "lookAtPosition": [0.0, 0.0, 0.0]}, "isSpeedbased": false, "lookAtValue": 0.01, "waypoints": [{"id": 613, "nextPointId": 614, "startTime": 2.0, "endTime": 4.0, "duration": 2.0, "point": [-3.0, 0.0, 1.0]}, {"id": 614, "nextPointId": null, "startTime": 4.0, "endTime": 7.0, "duration": 3.0, "point": [-6.0, 0.0, -2.0]}]}}]}}]}]}}