{"collaboration": false, "id": 1521, "cameraType": "Back Camera", "storyName": "Master December 2022", "experience": "AR", "mainStory": {"nodes": [{"name": "Scene1", "synopsis": "", "custom_name": "", "startTime": 0.0, "endTime": 11.44, "nodeId": 0, "nextNodeId": -1, "nodeType": "SceneNode", "nodeElements": [{"id": 4565, "order": 0, "node": 8135, "elementType": "Character", "character": {"objectId": 4565, "id": 2719, "name": "ironman", "dimensions": [0.0, 0.0, 0.0], "startTime": 0.0, "endTime": 11.44, "duration": 11.44, "layer": 1, "material": "...", "objectDbHash": 190, "origin": {"position": [0.0, 0.0, 0.0], "rotation": [0.0, 0.0, 0.0]}, "polygonCount": 0, "presenceDuration": 11.44, "rigType": "Humanoid", "scale": 1.0, "type": "Character", "iOSAssetBundle": "https://d1t9nnxfnhkozl.cloudfront.net/media/iOSiron_man_yXFCZnw.bundle", "webglAssetBundle": "https://d1t9nnxfnhkozl.cloudfront.net/media/WebGLiron_man_o4viCJd.bundle", "AndroidAssetBundle": "https://d1t9nnxfnhkozl.cloudfront.net/media/Androidiron_man_JX1NrcJ.bundle", "image_url": "https://d1t9nnxfnhkozl.cloudfront.net/media/thumbnail/iron_man_nXsPRRT.png", "characterElements": [{"id": 664, "type": "TextToSpeech", "node_element": 4565, "elementType": "TextToSpeech", "textToSpeech": {"id": 664, "country": "English (US)", "gender": "Male", "text": "I am Iron Man", "language": "en-US", "voiceEffect": "en-US-Standard-B", "voiceName": "en-US-Standard-B", "voiceVolume": 1.0, "startTime": 0.0, "endTime": 1.44, "duration": 1.44}, "start": 0.0}, {"id": 665, "type": "TextToSpeech", "node_element": 4565, "elementType": "TextToSpeech", "textToSpeech": {"id": 665, "country": "English (US)", "gender": "Male", "text": "I am very cool", "language": "en-US", "voiceEffect": "en-US-Standard-B", "voiceName": "en-US-Standard-B", "voiceVolume": 0.2, "startTime": 1.83, "endTime": 3.18, "duration": 1.345}, "start": 1.83}]}}]}]}}