{"collaboration": false, "id": 1329, "cameraType": "Back Camera", "storyName": "birthday celebration", "experience": "AR", "mainStory": {"nodes": [{"name": "Scene1", "startTime": 0.0, "endTime": 10.0, "nodeId": 0, "nextNodeId": -1, "nodeType": "SceneNode", "nodeElements": [{"id": 3794, "order": 0, "node_id": 5203, "elementType": "Character", "character": {"objectId": 3794, "id": 2261, "name": "Spidey", "dimensions": [0.0, 0.0, 0.0], "startTime": 0.0, "endTime": 10.0, "duration": 10.0, "layer": 1, "material": "...", "objectDbHash": 20, "origin": {"position": [0.09241044521331787, 0.12912464141845703, 0.0], "rotation": [0.0, 0.0, 0.0]}, "polygonCount": 0, "presenceDuration": 10.0, "rigType": "Humanoid", "scale": 1.0, "type": "Character", "iOSAssetBundle": "https://abxr-backend.s3.amazonaws.com/media/iOSspidey_TfcsmrJ.bundle", "webglAssetBundle": "https://abxr-backend.s3.amazonaws.com/media/WebGLspidey_NYSaA8R.bundle", "AndroidAssetBundle": "https://abxr-backend.s3.amazonaws.com/media/WebGLspidey_4NmSPLA.bundle", "image_url": "https://abxr-backend.s3.amazonaws.com/media/Spidey_64en4zA.png", "characterElements": [{"id": 815, "type": "Animation", "node_element": 3794, "elementType": "Animation", "animation": {"id": 815, "animationId": 67, "destination": {"position": [0.0, 0.0, 0.0], "rotation": [0.0, 0.0, 0.0]}, "AndroidAssetBundle": null, "iOSAssetBundle": null, "webglAssetBundle": null, "loopCount": 1, "name": "Dancing", "endTime": 10.0, "startTime": 0.0, "duration": 10.0, "trim": 0, "blend": "none", "stitch": null, "jointsCount": 0, "inverseKinematics": null, "rig": "", "animation_type": "In Movement", "type_of_animation": "In Movement", "category": null}, "start": 0.0, "movementFields": {}}, {"id": 418, "type": "Effect", "node_element": 3794, "elementType": "Effect", "effect": {"id": 418, "intId": 418, "objectId": 418, "type": "Effect", "image_url": "https://abxr-backend.s3.amazonaws.com/media/FX_Confetti_Falling_01.gif", "prefabName": "FX_Confetti_Falling_01", "iOSAssetBundle": null, "webglAssetBundle": null, "AndroidAssetBundle": null, "objectDbHash": 21, "mediaId": 21, "name": "FX_Confetti_Falling_01", "effectType": "2D", "position": [0.0, 0.0, 1.0], "rotation": [0.0, 0.0, 0.0], "scale": 1.0, "startTime": 0.0, "endTime": 10.0, "presenceDuration": 10.0, "duration": 10.0, "loop": false}, "start": 0.0}]}}, {"id": 3795, "order": 1, "node_id": 5203, "elementType": "Character", "character": {"objectId": 3795, "id": 2262, "name": "Fox blue", "dimensions": [0.0, 0.0, 0.0], "startTime": 0.0, "endTime": 10.0, "duration": 10.0, "layer": 1, "material": "...", "objectDbHash": 26, "origin": {"position": [-1.0117546319961548, 0.0, 0.0], "rotation": [0.0, 0.0, 0.0]}, "polygonCount": 0, "presenceDuration": 10.0, "rigType": "Humanoid", "scale": 1.0, "type": "Character", "iOSAssetBundle": "https://abxr-backend.s3.amazonaws.com/media/iOSfox-blue.bundle", "webglAssetBundle": "https://abxr-backend.s3.amazonaws.com/media/WebGLfox-blue_XxYllqe.bundle", "AndroidAssetBundle": "https://abxr-backend.s3.amazonaws.com/media/WebGLfox-blue.bundle", "image_url": "https://abxr-backend.s3.amazonaws.com/media/Fox-blue.png", "characterElements": [{"id": 816, "type": "Animation", "node_element": 3795, "elementType": "Animation", "animation": {"id": 816, "animationId": 73, "destination": {"position": [0.0, 0.0, 0.0], "rotation": [0.0, 0.0, 0.0]}, "AndroidAssetBundle": null, "iOSAssetBundle": null, "webglAssetBundle": null, "loopCount": 1, "name": "Slide Hip Hop Dance", "endTime": 10.0, "startTime": 0.0, "duration": 10.0, "trim": 0, "blend": "none", "stitch": null, "jointsCount": 0, "inverseKinematics": "[object Object]", "rig": "", "animation_type": "In Movement", "type_of_animation": "In Movement", "category": ["In movement"]}, "start": 0.0, "movementFields": {}}, {"id": 419, "type": "Effect", "node_element": 3795, "elementType": "Effect", "effect": {"id": 419, "intId": 419, "objectId": 419, "type": "Effect", "image_url": "https://abxr-backend.s3.amazonaws.com/media/FX_Confetti_Falling_01.gif", "prefabName": "FX_Confetti_Falling_01", "iOSAssetBundle": null, "webglAssetBundle": null, "AndroidAssetBundle": null, "objectDbHash": 21, "mediaId": 21, "name": "FX_Confetti_Falling_01", "effectType": "2D", "position": [0.0, 0.0, 1.0], "rotation": [0.0, 0.0, 0.0], "scale": 1.0, "startTime": 0.0, "endTime": 10.0, "presenceDuration": 10.0, "duration": 10.0, "loop": false}, "start": 0.0}]}}, {"id": 3796, "order": 2, "node_id": 5203, "elementType": "Character", "character": {"objectId": 3796, "id": 2263, "name": "Carton girl Update", "dimensions": [0.0, 0.0, 0.0], "startTime": 0.0, "endTime": 10.0, "duration": 10.0, "layer": 1, "material": "0", "objectDbHash": 3, "origin": {"position": [1.2375121116638184, 0.0, 0.0], "rotation": [0.0, 0.0, 0.0]}, "polygonCount": 0, "presenceDuration": 10.0, "rigType": "Humanoid", "scale": 0.66, "type": "Character", "iOSAssetBundle": "https://abxr-backend.s3.amazonaws.com/media/WebGl_cxwAB9o", "webglAssetBundle": "https://abxr-backend.s3.amazonaws.com/media/WebGl", "AndroidAssetBundle": "https://abxr-backend.s3.amazonaws.com/media/WebGl_oNk9Qa6", "image_url": "https://abxr-backend.s3.amazonaws.com/media/-Mvi7QCGgu4CJKm_pCRz.jpg", "characterElements": [{"id": 817, "type": "Animation", "node_element": 3796, "elementType": "Animation", "animation": {"id": 817, "animationId": 73, "destination": {"position": [0.0, 0.0, 0.0], "rotation": [0.0, 0.0, 0.0]}, "AndroidAssetBundle": null, "iOSAssetBundle": null, "webglAssetBundle": null, "loopCount": 1, "name": "Slide Hip Hop Dance", "endTime": 10.0, "startTime": 0.0, "duration": 10.0, "trim": 0, "blend": "none", "stitch": null, "jointsCount": 0, "inverseKinematics": "[object Object]", "rig": "", "animation_type": "In Movement", "type_of_animation": "In Movement", "category": ["In movement"]}, "start": 0.0, "movementFields": {}}, {"id": 420, "type": "Effect", "node_element": 3796, "elementType": "Effect", "effect": {"id": 420, "intId": 420, "objectId": 420, "type": "Effect", "image_url": "https://abxr-backend.s3.amazonaws.com/media/FX_Confetti_Falling_01.gif", "prefabName": "FX_Confetti_Falling_01", "iOSAssetBundle": null, "webglAssetBundle": null, "AndroidAssetBundle": null, "objectDbHash": 21, "mediaId": 21, "name": "FX_Confetti_Falling_01", "effectType": "2D", "position": [0.0, 0.0, 1.0], "rotation": [0.0, 0.0, 0.0], "scale": 1.0, "startTime": 0.0, "endTime": 10.0, "presenceDuration": 10.0, "duration": 10.0, "loop": false}, "start": 0.0}]}}, {"id": 3799, "order": 3, "node_id": 5203, "elementType": "Object3D", "object3D": {"objectId": 3799, "id": 1146, "name": "plane", "dimensions": [0.0, 0.0, 0.0], "startTime": 0.0, "endTime": 10.0, "duration": 10.0, "layer": 1, "material": "...", "objectDbHash": 104, "origin": {"position": [0.0, 0.0, 0.0], "rotation": [0.0, 0.0, 0.0]}, "polygonCount": 0, "presenceDuration": 10.0, "rigType": "Humanoid", "scale": 1.0, "type": "Object3D", "iOSAssetBundle": "https://abxr-backend.s3.amazonaws.com/media/iOSplane_lP4ZPc8.bundle", "webglAssetBundle": "https://abxr-backend.s3.amazonaws.com/media/WebGLplane_9SYzQa6.bundle", "AndroidAssetBundle": "https://abxr-backend.s3.amazonaws.com/media/WebGLplane_hbKslwc.bundle", "image_url": "https://abxr-backend.s3.amazonaws.com/media/thumbnail/plane_7ZvupJL.png", "object3DElements": []}}]}]}}