{"collaboration": false, "id": 2196, "cameraType": "Back Camera", "storyName": "My S Project", "experience": "AR", "mainStory": {"nodes": [{"name": "Scene1", "synopsis": "", "custom_name": "", "startTime": 0.0, "endTime": 10.0, "nodeId": 0, "nextNodeId": -1, "nodeType": "SceneNode", "nodeElements": [{"id": 5221, "order": 0, "node": 9591, "elementType": "Effect", "effect": {"id": 526, "intId": 526, "objectId": 5221, "type": "Effect", "image_url": "https://d1t9nnxfnhkozl.cloudfront.net/media/20220412_112645.gif", "prefabName": "FX_Dust_Big_01", "iOSAssetBundle": null, "webglAssetBundle": null, "AndroidAssetBundle": null, "objectDbHash": 25, "mediaId": 25, "name": "FX_Dust_Big_01", "effectType": "2D", "position": [0.0, 0.0, 0.0], "rotation": [0.0, 0.0, 0.0], "scale": 1.0, "startTime": 0.0, "endTime": 10.0, "presenceDuration": 10.0, "duration": 10.0, "loop": false}}, {"id": 5222, "order": 0, "node": 9591, "elementType": "Effect", "effect": {"id": 527, "intId": 527, "objectId": 5222, "type": "Effect", "image_url": "https://d1t9nnxfnhkozl.cloudfront.net/media/20220412_112645.gif", "prefabName": "FX_Dust_Big_01", "iOSAssetBundle": null, "webglAssetBundle": null, "AndroidAssetBundle": null, "objectDbHash": 25, "mediaId": 25, "name": "FX_Dust_Big_01", "effectType": "2D", "position": [0.0, 0.0, 0.0], "rotation": [0.0, 0.0, 0.0], "scale": 1.0, "startTime": 0.0, "endTime": 10.0, "presenceDuration": 10.0, "duration": 10.0, "loop": false}}]}]}}