{"collaboration": false, "id": 2509, "cameraType": "Back Camera", "storyName": "testM", "experience": "AR", "trackingOptions": {"trackingType": "PlaneDetection", "planeDetection": {"detectionType": "Horizontal", "planeType": "TBD"}}, "mainStory": {"nodes": [{"created_at": "2023-03-22T11:06:33.947361Z", "updated_at": "2023-03-22T11:06:41.322039Z", "name": "Scene1", "synopsis": "", "custom_name": "", "startTime": 0.0, "endTime": 10.0, "nodeId": 0, "nextNodeId": 2, "nodeType": "SceneNode", "nodeElements": [{"id": 6375, "created_at": "2023-03-22T11:07:55.802063Z", "updated_at": "2023-03-22T11:07:55.802090Z", "type": "Character", "order": 0, "node": 11493, "elementType": "Character", "character": {"objectId": 3500, "id": "node_character_3500", "name": "SpaceGirl", "dimensions": [0.0, 0.0, 0.0], "startTime": 0.0, "endTime": 10.0, "duration": 10.0, "layer": 1, "material": "...", "objectDbHash": 234, "origin": {"position": [0.0, 0.0, 0.0], "rotation": [0.0, 190.0, 0.0]}, "polygonCount": 0, "presenceDuration": 10.0, "rigType": "Humanoid", "scale": 2.29, "type": "Character", "iOSAssetBundle": "https://d1t9nnxfnhkozl.cloudfront.net/media/iOSspacegirl_pose_ycMZLS4.bundle", "webglAssetBundle": "https://d1t9nnxfnhkozl.cloudfront.net/media/WebGLspacegirl_pose_rUS2o0X.bundle", "AndroidAssetBundle": "https://d1t9nnxfnhkozl.cloudfront.net/media/Androidspacegirl_pose_svrtTLd.bundle", "image_url": "https://d1t9nnxfnhkozl.cloudfront.net/media/thumbnail/SpaceGirl_pose_AqD25gY.png", "characterElements": []}}, {"id": 6376, "created_at": "2023-03-22T11:07:55.873251Z", "updated_at": "2023-03-22T11:07:55.873277Z", "type": "Character", "order": 0, "node": 11493, "elementType": "Character", "character": {"objectId": 3501, "id": "node_character_3501", "name": "SpaceGirl", "dimensions": [0.0, 0.0, 0.0], "startTime": 0.0, "endTime": 10.0, "duration": 10.0, "layer": 1, "material": "...", "objectDbHash": 234, "origin": {"position": [0.0, 0.0, 0.0], "rotation": [0.0, 190.0, 0.0]}, "polygonCount": 0, "presenceDuration": 10.0, "rigType": "Humanoid", "scale": 0.66, "type": "Character", "iOSAssetBundle": "https://d1t9nnxfnhkozl.cloudfront.net/media/iOSspacegirl_pose_ycMZLS4.bundle", "webglAssetBundle": "https://d1t9nnxfnhkozl.cloudfront.net/media/WebGLspacegirl_pose_rUS2o0X.bundle", "AndroidAssetBundle": "https://d1t9nnxfnhkozl.cloudfront.net/media/Androidspacegirl_pose_svrtTLd.bundle", "image_url": "https://d1t9nnxfnhkozl.cloudfront.net/media/thumbnail/SpaceGirl_pose_AqD25gY.png", "characterElements": []}}]}, {"created_at": "2023-03-22T11:06:34.180572Z", "updated_at": "2023-03-22T11:06:34.180597Z", "name": "Scene1", "synopsis": "", "custom_name": "", "startTime": 0.0, "endTime": 0.0, "nodeId": 1, "nextNodeId": -1, "nodeType": "SceneNode", "nodeElements": []}, {"created_at": "2023-03-22T11:06:41.002020Z", "updated_at": "2023-03-22T11:06:41.002050Z", "name": "Logic2", "synopsis": "", "custom_name": "", "conditions": [{"conditionType": "Touch", "touch": {"interactionType": "doubleTap", "nextNodeId": 3, "objectId": 6376, "priority": 1, "touchType": "3D"}}, {"conditionType": "Touch", "touch": {"interactionType": "doubleTap", "nextNodeId": 4, "objectId": 6376, "priority": 1, "touchType": "3D"}}, {"conditionType": "Touch", "touch": {"interactionType": "doubleTap", "nextNodeId": 5, "objectId": 6376, "priority": 1, "touchType": "3D"}}], "nodeType": "LogicNode", "nodeId": 2}, {"created_at": "2023-03-22T11:06:41.002020Z", "updated_at": "2023-03-22T11:06:41.002050Z", "name": "Logic2", "synopsis": "", "custom_name": "", "conditions": [{"conditionType": "Touch", "touch": {"interactionType": "doubleTap", "nextNodeId": 3, "objectId": 6376, "priority": 1, "touchType": "3D"}}, {"conditionType": "Touch", "touch": {"interactionType": "doubleTap", "nextNodeId": 4, "objectId": 6376, "priority": 1, "touchType": "3D"}}, {"conditionType": "Touch", "touch": {"interactionType": "doubleTap", "nextNodeId": 5, "objectId": 6376, "priority": 1, "touchType": "3D"}}], "nodeType": "LogicNode", "nodeId": 2}, {"created_at": "2023-03-22T11:06:41.002020Z", "updated_at": "2023-03-22T11:06:41.002050Z", "name": "Logic2", "synopsis": "", "custom_name": "", "conditions": [{"conditionType": "Touch", "touch": {"interactionType": "doubleTap", "nextNodeId": 3, "objectId": 6376, "priority": 1, "touchType": "3D"}}, {"conditionType": "Touch", "touch": {"interactionType": "doubleTap", "nextNodeId": 4, "objectId": 6376, "priority": 1, "touchType": "3D"}}, {"conditionType": "Touch", "touch": {"interactionType": "doubleTap", "nextNodeId": 5, "objectId": 6376, "priority": 1, "touchType": "3D"}}], "nodeType": "LogicNode", "nodeId": 2}, {"created_at": "2023-03-22T11:08:34.156520Z", "updated_at": "2023-03-22T11:08:34.156546Z", "name": "Scene2", "synopsis": "", "custom_name": "", "startTime": 0.0, "endTime": 10.0, "nodeId": 3, "nextNodeId": -1, "nodeType": "SceneNode", "nodeElements": [{"id": 6378, "created_at": "2023-03-22T11:08:35.204487Z", "updated_at": "2023-03-22T11:08:35.204503Z", "type": "Character", "order": 0, "node": 11496, "elementType": "Character", "character": {"objectId": 3503, "id": "node_character_3503", "name": "SpaceGirl", "dimensions": [0.0, 0.0, 0.0], "startTime": 0.0, "endTime": 10.0, "duration": 10.0, "layer": 1, "material": "...", "objectDbHash": 234, "origin": {"position": [0.0, 0.0, 0.0], "rotation": [0.0, 190.0, 0.0]}, "polygonCount": 0, "presenceDuration": 10.0, "rigType": "Humanoid", "scale": 0.66, "type": "Character", "iOSAssetBundle": "https://d1t9nnxfnhkozl.cloudfront.net/media/iOSspacegirl_pose_ycMZLS4.bundle", "webglAssetBundle": "https://d1t9nnxfnhkozl.cloudfront.net/media/WebGLspacegirl_pose_rUS2o0X.bundle", "AndroidAssetBundle": "https://d1t9nnxfnhkozl.cloudfront.net/media/Androidspacegirl_pose_svrtTLd.bundle", "image_url": "https://d1t9nnxfnhkozl.cloudfront.net/media/thumbnail/SpaceGirl_pose_AqD25gY.png", "characterElements": []}}, {"id": 6383, "created_at": "2023-03-22T11:09:30.768277Z", "updated_at": "2023-03-22T11:09:30.768305Z", "type": "Object3D", "order": 1, "node": 11496, "elementType": "Object3D", "object3D": {"objectId": 2230, "id": "node_object3D_2230", "name": "tree root 1", "dimensions": [0.0, 0.0, 0.0], "startTime": 0.0, "endTime": 10.0, "duration": 10.0, "layer": 1, "material": "{'id': 0, 'name': '...'}", "objectDbHash": 618, "origin": {"position": [2.0, 0.0, 0.0], "rotation": [0.0, 0.0, 0.0]}, "polygonCount": 0, "presenceDuration": 10.0, "rigType": "Humanoid", "scale": 1.0, "type": "Object3D", "iOSAssetBundle": "https://d1t9nnxfnhkozl.cloudfront.net/media/iOStreeroot_V5Os8TL.bundle", "webglAssetBundle": "https://d1t9nnxfnhkozl.cloudfront.net/media/WebGLtreeroot_WErcVhG.bundle", "AndroidAssetBundle": "https://d1t9nnxfnhkozl.cloudfront.net/media/Androidtreeroot_5z1WCtw.bundle", "image_url": "https://d1t9nnxfnhkozl.cloudfront.net/media/thumbnail/treeroot_CCBC7Ux.png", "object3DElements": []}}, {"id": 6384, "created_at": "2023-03-22T11:09:30.825273Z", "updated_at": "2023-03-22T11:09:30.825301Z", "type": "Object3D", "order": 1, "node": 11496, "elementType": "Object3D", "object3D": {"objectId": 2231, "id": "node_object3D_2231", "name": "tree root 1", "dimensions": [0.0, 0.0, 0.0], "startTime": 0.0, "endTime": 10.0, "duration": 10.0, "layer": 1, "material": "{'id': 0, 'name': '...'}", "objectDbHash": 618, "origin": {"position": [2.0, 0.0, 0.0], "rotation": [0.0, 0.0, 0.0]}, "polygonCount": 0, "presenceDuration": 10.0, "rigType": "Humanoid", "scale": 1.0, "type": "Object3D", "iOSAssetBundle": "https://d1t9nnxfnhkozl.cloudfront.net/media/iOStreeroot_V5Os8TL.bundle", "webglAssetBundle": "https://d1t9nnxfnhkozl.cloudfront.net/media/WebGLtreeroot_WErcVhG.bundle", "AndroidAssetBundle": "https://d1t9nnxfnhkozl.cloudfront.net/media/Androidtreeroot_5z1WCtw.bundle", "image_url": "https://d1t9nnxfnhkozl.cloudfront.net/media/thumbnail/treeroot_CCBC7Ux.png", "object3DElements": []}}, {"id": 6385, "created_at": "2023-03-22T11:09:30.868203Z", "updated_at": "2023-03-22T11:09:30.868232Z", "type": "Object3D", "order": 1, "node": 11496, "elementType": "Object3D", "object3D": {"objectId": 2232, "id": "node_object3D_2232", "name": "tree root 1", "dimensions": [0.0, 0.0, 0.0], "startTime": 0.0, "endTime": 10.0, "duration": 10.0, "layer": 1, "material": "{'id': 0, 'name': '...'}", "objectDbHash": 618, "origin": {"position": [2.0, 0.0, 0.0], "rotation": [0.0, 0.0, 0.0]}, "polygonCount": 0, "presenceDuration": 10.0, "rigType": "Humanoid", "scale": 1.0, "type": "Object3D", "iOSAssetBundle": "https://d1t9nnxfnhkozl.cloudfront.net/media/iOStreeroot_V5Os8TL.bundle", "webglAssetBundle": "https://d1t9nnxfnhkozl.cloudfront.net/media/WebGLtreeroot_WErcVhG.bundle", "AndroidAssetBundle": "https://d1t9nnxfnhkozl.cloudfront.net/media/Androidtreeroot_5z1WCtw.bundle", "image_url": "https://d1t9nnxfnhkozl.cloudfront.net/media/thumbnail/treeroot_CCBC7Ux.png", "object3DElements": []}}]}, {"created_at": "2023-03-22T11:08:34.187586Z", "updated_at": "2023-03-22T11:08:34.187613Z", "name": "Scene2", "synopsis": "", "custom_name": "", "startTime": 0.0, "endTime": 10.0, "nodeId": 4, "nextNodeId": -1, "nodeType": "SceneNode", "nodeElements": [{"id": 6379, "created_at": "2023-03-22T11:08:35.344632Z", "updated_at": "2023-03-22T11:08:35.344659Z", "type": "Character", "order": 0, "node": 11497, "elementType": "Character", "character": {"objectId": 3504, "id": "node_character_3504", "name": "SpaceGirl", "dimensions": [0.0, 0.0, 0.0], "startTime": 0.0, "endTime": 10.0, "duration": 10.0, "layer": 1, "material": "...", "objectDbHash": 234, "origin": {"position": [0.0, 0.0, 0.0], "rotation": [0.0, 190.0, 0.0]}, "polygonCount": 0, "presenceDuration": 10.0, "rigType": "Humanoid", "scale": 2.29, "type": "Character", "iOSAssetBundle": "https://d1t9nnxfnhkozl.cloudfront.net/media/iOSspacegirl_pose_ycMZLS4.bundle", "webglAssetBundle": "https://d1t9nnxfnhkozl.cloudfront.net/media/WebGLspacegirl_pose_rUS2o0X.bundle", "AndroidAssetBundle": "https://d1t9nnxfnhkozl.cloudfront.net/media/Androidspacegirl_pose_svrtTLd.bundle", "image_url": "https://d1t9nnxfnhkozl.cloudfront.net/media/thumbnail/SpaceGirl_pose_AqD25gY.png", "characterElements": []}}, {"id": 6380, "created_at": "2023-03-22T11:08:35.350039Z", "updated_at": "2023-03-22T11:08:35.350054Z", "type": "Character", "order": 0, "node": 11497, "elementType": "Character", "character": {"objectId": 3505, "id": "node_character_3505", "name": "SpaceGirl", "dimensions": [0.0, 0.0, 0.0], "startTime": 0.0, "endTime": 10.0, "duration": 10.0, "layer": 1, "material": "...", "objectDbHash": 234, "origin": {"position": [0.0, 0.0, 0.0], "rotation": [0.0, 190.0, 0.0]}, "polygonCount": 0, "presenceDuration": 10.0, "rigType": "Humanoid", "scale": 0.66, "type": "Character", "iOSAssetBundle": "https://d1t9nnxfnhkozl.cloudfront.net/media/iOSspacegirl_pose_ycMZLS4.bundle", "webglAssetBundle": "https://d1t9nnxfnhkozl.cloudfront.net/media/WebGLspacegirl_pose_rUS2o0X.bundle", "AndroidAssetBundle": "https://d1t9nnxfnhkozl.cloudfront.net/media/Androidspacegirl_pose_svrtTLd.bundle", "image_url": "https://d1t9nnxfnhkozl.cloudfront.net/media/thumbnail/SpaceGirl_pose_AqD25gY.png", "characterElements": []}}]}, {"created_at": "2023-03-22T11:08:34.221494Z", "updated_at": "2023-03-22T11:08:34.221523Z", "name": "Scene2", "synopsis": "", "custom_name": "", "startTime": 0.0, "endTime": 10.0, "nodeId": 5, "nextNodeId": -1, "nodeType": "SceneNode", "nodeElements": [{"id": 6381, "created_at": "2023-03-22T11:08:36.191527Z", "updated_at": "2023-03-22T11:08:36.191555Z", "type": "Character", "order": 0, "node": 11498, "elementType": "Character", "character": {"objectId": 3506, "id": "node_character_3506", "name": "SpaceGirl", "dimensions": [0.0, 0.0, 0.0], "startTime": 0.0, "endTime": 10.0, "duration": 10.0, "layer": 1, "material": "...", "objectDbHash": 234, "origin": {"position": [0.0, 0.0, 0.0], "rotation": [0.0, 190.0, 0.0]}, "polygonCount": 0, "presenceDuration": 10.0, "rigType": "Humanoid", "scale": 2.29, "type": "Character", "iOSAssetBundle": "https://d1t9nnxfnhkozl.cloudfront.net/media/iOSspacegirl_pose_ycMZLS4.bundle", "webglAssetBundle": "https://d1t9nnxfnhkozl.cloudfront.net/media/WebGLspacegirl_pose_rUS2o0X.bundle", "AndroidAssetBundle": "https://d1t9nnxfnhkozl.cloudfront.net/media/Androidspacegirl_pose_svrtTLd.bundle", "image_url": "https://d1t9nnxfnhkozl.cloudfront.net/media/thumbnail/SpaceGirl_pose_AqD25gY.png", "characterElements": []}}, {"id": 6382, "created_at": "2023-03-22T11:08:36.197227Z", "updated_at": "2023-03-22T11:08:36.197241Z", "type": "Character", "order": 0, "node": 11498, "elementType": "Character", "character": {"objectId": 3507, "id": "node_character_3507", "name": "SpaceGirl", "dimensions": [0.0, 0.0, 0.0], "startTime": 0.0, "endTime": 10.0, "duration": 10.0, "layer": 1, "material": "...", "objectDbHash": 234, "origin": {"position": [0.0, 0.0, 0.0], "rotation": [0.0, 190.0, 0.0]}, "polygonCount": 0, "presenceDuration": 10.0, "rigType": "Humanoid", "scale": 0.66, "type": "Character", "iOSAssetBundle": "https://d1t9nnxfnhkozl.cloudfront.net/media/iOSspacegirl_pose_ycMZLS4.bundle", "webglAssetBundle": "https://d1t9nnxfnhkozl.cloudfront.net/media/WebGLspacegirl_pose_rUS2o0X.bundle", "AndroidAssetBundle": "https://d1t9nnxfnhkozl.cloudfront.net/media/Androidspacegirl_pose_svrtTLd.bundle", "image_url": "https://d1t9nnxfnhkozl.cloudfront.net/media/thumbnail/SpaceGirl_pose_AqD25gY.png", "characterElements": []}}]}]}}